humblelion/__init__.py
humblelion/httpbot.py
humblelion/humblelion.py
humblelion-0.0.2.dist-info/DESCRIPTION.rst
humblelion-0.0.2.dist-info/METADATA
humblelion-0.0.2.dist-info/RECORD
humblelion-0.0.2.dist-info/WHEEL
humblelion-0.0.2.dist-info/entry_points.txt
humblelion-0.0.2.dist-info/metadata.json
humblelion-0.0.2.dist-info/top_level.txt
