Metadata-Version: 2.0
Name: humblelion
Version: 0.0.2
Summary: An unofficial Humble Bundle API for listing and downloading games and bundles
Home-page: https://github.com/MestreLion/humblebundle
Author: Rodrigo Silva
Author-email: linux@rodrigosilva.com
License: GPLv3+
Keywords: api
Platform: UNKNOWN
Classifier: Development Status :: 3 - Alpha
Classifier: Intended Audience :: Developers
Classifier: Intended Audience :: End Users/Desktop
Classifier: Topic :: Games/Entertainment
Classifier: License :: OSI Approved :: GNU General Public License v3 or later (GPLv3+)
Classifier: Programming Language :: Python :: 2
Classifier: Programming Language :: Python :: 2.7
Classifier: Programming Language :: Python :: 3
Classifier: Programming Language :: Python :: 3.6
Requires-Dist: keyring
Requires-Dist: lxml
Requires-Dist: progressbar2
Requires-Dist: pyxdg
Requires-Dist: dbus-python
Requires-Dist: secretstorage
